seedoo/tensorrt_utils/__init__.py
seedoo/tensorrt_utils/utils/__init__.py
seedoo/tensorrt_utils/utils/convertor.py
seedoo/tensorrt_utils/utils/pipeline.py
seedoo/tensorrt_utils/utils/predictor.py
seedoo/tensorrt_utils/utils/tests/__init__.py
testmyseedoo-1.1.dist-info/METADATA
testmyseedoo-1.1.dist-info/WHEEL
testmyseedoo-1.1.dist-info/top_level.txt
testmyseedoo-1.1.dist-info/RECORD
