Metadata-Version: 2.1
Name: testmyseedoo
Version: 1.1
Summary: this package contains tools for conversion model to engine and get inference with it
License: UNKNOWN
Platform: UNKNOWN
